Workbook

Sheet 前提条件
A1: UNLID 財務モデル 前提条件
A2: 作成日：2026年3月 | 単位：万円 | 中央値シナリオ
A4: ① 売上ドライバー
A5: 項目 | B5: Year1 | C5: Year2 | D5: Year3
A6: B2B契約企業数（期末） | B6: 10 | C6: 50 | D6: 160
A7: FDE受託平均月額（万円） | B7: 15 | C7: 18 | D7: 20
A8: B2B受託収益（万円） | B8: =B6*B7*12 | C8: =C6*C7*12 | D8: =D6*D7*12
A9: 人材紹介件数 | B9: 3 | C9: 20 | D9: 50
A10: 紹介フィー単価（万円） | B10: 140 | C10: 140 | D10: 140
A11: 人材紹介フィー（万円） | B11: =B9*B10 | C11: =C9*C10 | D11: =D9*D10
A12: プロジェクト件数 | B12: 0 | C12: 5 | D12: 15
A13: プロジェクト単価（万円） | B13: 0 | C13: 160 | D13: 160
A14: プロジェクト収益（万円） | B14: =B12*B13 | C14: =C12*C13 | D14: =D12*D13
A15: 売上合計（万円） | B15: =B8+B11+B14 | C15: =C8+C11+C14 | D15: =D8+D11+D14
A17: ② コストドライバー
A18: 項目 | B18: Year1 | C18: Year2 | D18: Year3
A19: FDE正社員数 | B19: 2 | C19: 10 | D19: 32
A20: FDE月額人件費（万円） | B20: 45 | C20: 40 | D20: 42
A21: FDE人件費合計（万円） | B21: =B19*B20*12 | C21: =C19*C20*12 | D21: =D19*D20*12
A22: 創業者報酬（万円） | B22: 360 | C22: 600 | D22: 840
A23: 管理スタッフ人件費 | B23: 0 | C23: 1080 | D23: 3360
A24: 人件費合計（万円） | B24: =B21+B22+B23 | C24: =C21+C22+C23 | D24: =D21+D22+D23
A25: ワーカー報酬率（%） | B25: 0.09 | C25: 0.08 | D25: 0.08
A26: ワーカー報酬（万円） | B26: =前提条件!B15*B25 | C26: =前提条件!C15*C25 | D26: =前提条件!D15*D25
A27: オフィス・インフラ費 | B27: 180 | C27: 360 | D27: 600
A28: マーケティング費 | B28: 120 | C28: 360 | D28: 600
A29: 法務・許認可費 | B29: 200 | C29: 300 | D29: 400
A30: 採用費 | B30: 0 | C30: 500 | D30: 1500
A31: システム開発費 | B31: 100 | C31: 300 | D31: 800
A32: その他 | B32: 100 | C32: 200 | D32: 400
A33: 販管費合計（万円） | B33: =B24+B27+B28+B29+B30+B31+B32 | C33: =C24+C27+C28+C29+C30+C31+C32 | D33: =D24+D27+D28+D29+D30+D31+D32
A35: ③ その他前提
A36: 項目 | B36: Year1 | C36: Year2 | D36: Year3
A37: 実効税率 | B37: 0.3 | C37: 0.3 | D37: 0.3
A38: 減価償却費（万円） | B38: 20 | C38: 80 | D38: 200
A39: 設備投資（Capex）（万円） | B39: 100 | C39: 300 | D39: 800
A40: 初期調達資本（万円） | B40: 2000 | C40: 0 | D40: 0
A41: 運転資本回転日数（売掛） | B41: 30 | C41: 30 | D41: 30
A42: 買掛金回転日数 | B42: 15 | C42: 15 | D42: 15

Sheet PL（損益計算書）
A1: UNLID 損益計算書（P&L）3ヶ年
A2: 単位：万円（税引前） | 前提条件シートの数値と連動
A3: 項目 | B3: Year1 | C3: Year2 | D3: Year3 | E3: 3年累計
A4: 【売上高】
A5: B2B受託収益 | B5: =前提条件!B8 | C5: =前提条件!C8 | D5: =前提条件!D8 | E5: =SUM(B5:D5)
A6: 人材紹介フィー | B6: =前提条件!B11 | C6: =前提条件!C11 | D6: =前提条件!D11 | E6: =SUM(B6:D6)
A7: プロジェクト型受託 | B7: =前提条件!B14 | C7: =前提条件!C14 | D7: =前提条件!D14 | E7: =SUM(B7:D7)
A8: 売上合計 | B8: =SUM(B5:B7) | C8: =SUM(C5:C7) | D8: =SUM(D5:D7) | E8: =SUM(B8:D8)
A9: 前年比成長率 | B9: — | C9: =(C8-B8)/B8 | D9: =(D8-C8)/C8 | E9: —
A11: 【売上原価（変動費）】
A12: 副業ワーカー報酬 | B12: =前提条件!B26 | C12: =前提条件!C26 | D12: =前提条件!D26 | E12: =SUM(B12:D12)
A13: FDE外注費 | B13: =0 | C13: =200 | D13: =600 | E13: =SUM(B13:D13)
A14: 売上原価合計 | B14: =SUM(B12:B13) | C14: =SUM(C12:C13) | D14: =SUM(D12:D13) | E14: =SUM(B14:D14)
A16: 売上総利益（粗利） | B16: =B8-B14 | C16: =C8-C14 | D16: =D8-D14 | E16: =SUM(B16:D16)
A17: 粗利率 | B17: =B16/B8 | C17: =C16/C8 | D17: =D16/D8
A19: 【販売費及び一般管理費】
A20: FDE人件費 | B20: =前提条件!B21 | C20: =前提条件!C21 | D20: =前提条件!D21 | E20: =SUM(B20:D20)
A21: 創業者報酬 | B21: =前提条件!B22 | C21: =前提条件!C22 | D21: =前提条件!D22 | E21: =SUM(B21:D21)
A22: 管理・営業スタッフ費 | B22: =前提条件!B23 | C22: =前提条件!C23 | D22: =前提条件!D23 | E22: =SUM(B22:D22)
A23: オフィス・インフラ費 | B23: =前提条件!B27 | C23: =前提条件!C27 | D23: =前提条件!D27 | E23: =SUM(B23:D23)
A24: マーケティング費 | B24: =前提条件!B28 | C24: =前提条件!C28 | D24: =前提条件!D28 | E24: =SUM(B24:D24)
A25: 法務・許認可費 | B25: =前提条件!B29 | C25: =前提条件!C29 | D25: =前提条件!D29 | E25: =SUM(B25:D25)
A26: 採用費 | B26: =前提条件!B30 | C26: =前提条件!C30 | D26: =前提条件!D30 | E26: =SUM(B26:D26)
A27: システム開発費 | B27: =前提条件!B31 | C27: =前提条件!C31 | D27: =前提条件!D31 | E27: =SUM(B27:D27)
A28: その他 | B28: =前提条件!B32 | C28: =前提条件!C32 | D28: =前提条件!D32 | E28: =SUM(B28:D28)
A29: 販管費合計 | B29: =SUM(B20:B28) | C29: =SUM(C20:C28) | D29: =SUM(D20:D28) | E29: =SUM(B29:D29)
A30: 販管費率 | B30: =B29/B8 | C30: =C29/C8 | D30: =D29/D8
A32: 営業利益（EBIT） | B32: =B16-B29 | C32: =C16-C29 | D32: =D16-D29 | E32: =SUM(B32:D32)
A33: 営業利益率 | B33: =B32/B8 | C33: =C32/C8 | D33: =D32/D8
A34: (+) 減価償却費 | B34: =前提条件!B38 | C34: =前提条件!C38 | D34: =前提条件!D38
A35: EBITDA | B35: =B32+B34 | C35: =C32+C34 | D35: =D32+D34 | E35: =SUM(B35:D35)
A36: EBITDAマージン | B36: =B35/B8 | C36: =C35/C8 | D36: =D35/D8
A37: 法人税等（実効税率30%） | B37: =IF(B32>0,ROUND(B32*前提条件!B37,0),0) | C37: =IF(C32>0,ROUND(C32*前提条件!B37,0),0) | D37: =IF(D32>0,ROUND(D32*前提条件!B37,0),0)
A38: 当期純利益 | B38: =B32-B37 | C38: =C32-C37 | D38: =D32-D37 | E38: =SUM(B38:D38)
A39: 純利益率 | B39: =B38/B8 | C39: =C38/C8 | D39: =D38/D8

Sheet BS（貸借対照表）
A1: UNLID 貸借対照表（B/S）3ヶ年
A2: 単位：万円 | 期末残高 | PL・CF連動
A3: 項目 | B3: 期首（Year0） | C3: Year1末 | D3: Year2末 | E3: Year3末
A4: 【資産の部】
A5: 現金・預金 | B5: 2000 | C5: =B5+CF（キャッシュフロー計算書）!B20 | D5: =C5+CF（キャッシュフロー計算書）!C20 | E5: =D5+CF（キャッシュフロー計算書）!D20
A6: 売掛金 | B6: 0 | C6: =ROUND(PL（損益計算書）!B8*前提条件!B41/365,0) | D6: =ROUND(PL（損益計算書）!C8*前提条件!C41/365,0) | E6: =ROUND(PL（損益計算書）!D8*前提条件!D41/365,0)
A7: 前払費用・その他流動資産 | B7: 50 | C7: 50 | D7: 50 | E7: 50
A8: 流動資産合計 | B8: =SUM(B5:B7) | C8: =SUM(C5:C7) | D8: =SUM(D5:D7) | E8: =SUM(E5:E7)
A9: 固定資産（純額） | B9: 0 | C9: =B9+前提条件!B39-前提条件!B38 | D9: =C9+前提条件!C39-前提条件!C38 | E9: =D9+前提条件!D39-前提条件!D38
A10: 資産合計 | B10: =B8+B9 | C10: =C8+C9 | D10: =D8+D9 | E10: =E8+E9
A12: 【負債の部】
A13: 買掛金 | B13: 0 | C13: =ROUND(PL（損益計算書）!B14*前提条件!B42/365,0) | D13: =ROUND(PL（損益計算書）!C14*前提条件!C42/365,0) | E13: =ROUND(PL（損益計算書）!D14*前提条件!D42/365,0)
A14: 未払費用（人件費等） | B14: 0 | C14: =ROUND(前提条件!B24/12,0) | D14: =ROUND(前提条件!C24/12,0) | E14: =ROUND(前提条件!D24/12,0)
A15: 流動負債合計 | B15: =SUM(B13:B14) | C15: =SUM(C13:C14) | D15: =SUM(D13:D14) | E15: =SUM(E13:E14)
A16: 借入金・長期負債 | B16: 0 | C16: 0 | D16: 0 | E16: 0
A17: 負債合計 | B17: =B15+B16 | C17: =C15+C16 | D17: =D15+D16 | E17: =E15+E16
A19: 【純資産の部】
A20: 資本金・資本剰余金 | B20: 2000 | C20: =B20 | D20: =B20 | E20: =B20
A21: 利益剰余金（累積） | B21: 0 | C21: =B21+PL（損益計算書）!B38 | D21: =C21+PL（損益計算書）!C38 | E21: =D21+PL（損益計算書）!D38
A22: 純資産合計 | B22: =B20+B21 | C22: =C20+C21 | D22: =D20+D21 | E22: =E20+E21
A23: 負債・純資産合計 | B23: =B17+B22 | C23: =C17+C22 | D23: =D17+D22 | E23: =E17+E22
A24: ✓ バランスチェック（資産-負債純資産） | B24: =B10-B23 | C24: =C10-C23 | D24: =D10-D23 | E24: =E10-E23

Sheet CF（キャッシュフロー計算書）
A1: UNLID キャッシュフロー計算書（間接法）3ヶ年
A2: 単位：万円 | PL・BS連動 ※CF合計 = 現金増減に一致
A3: 項目 | B3: Year1 | C3: Year2 | D3: Year3 | E3: 3年累計
A4: 【営業活動によるCF】
A5: 当期純利益 | B5: =PL（損益計算書）!B38 | C5: =PL（損益計算書）!C38 | D5: =PL（損益計算書）!D38 | E5: =SUM(B5:D5)
A6: (+) 減価償却費（非資金費用） | B6: =前提条件!B38 | C6: =前提条件!C38 | D6: =前提条件!D38 | E6: =SUM(B6:D6)
A7: (-) 売掛金増加 | B7: =-(BS（貸借対照表）!C6-BS（貸借対照表）!B6) | C7: =-(BS（貸借対照表）!D6-BS（貸借対照表）!C6) | D7: =-(BS（貸借対照表）!E6-BS（貸借対照表）!D6) | E7: =SUM(B7:D7)
A8: (+) 買掛金増加 | B8: =BS（貸借対照表）!C13-BS（貸借対照表）!B13 | C8: =BS（貸借対照表）!D13-BS（貸借対照表）!C13 | D8: =BS（貸借対照表）!E13-BS（貸借対照表）!D13 | E8: =SUM(B8:D8)
A9: (-) 法人税等支払い | B9: =-PL（損益計算書）!B37 | C9: =-PL（損益計算書）!C37 | D9: =-PL（損益計算書）!D37 | E9: =SUM(B9:D9)
A10: 営業活動CF合計 | B10: =SUM(B5:B9) | C10: =SUM(C5:C9) | D10: =SUM(D5:D9) | E10: =SUM(B10:D10)
A12: 【投資活動によるCF】
A13: (-) 設備投資（Capex） | B13: =-前提条件!B39 | C13: =-前提条件!C39 | D13: =-前提条件!D39 | E13: =SUM(B13:D13)
A14: 投資活動CF合計 | B14: =B13 | C14: =C13 | D14: =D13 | E14: =SUM(B14:D14)
A16: 【財務活動によるCF】
A17: (+) 増資・資本調達 | B17: =前提条件!B40 | C17: =前提条件!C40 | D17: =前提条件!D40 | E17: =SUM(B17:D17)
A18: 財務活動CF合計 | B18: =B17 | C18: =C17 | D18: =D17 | E18: =SUM(B18:D18)
A20: 当期CF合計（純増減） | B20: =B10+B14+B18 | C20: =C10+C14+C18 | D20: =D10+D14+D18 | E20: =SUM(B20:D20)
A21: 期首現金残高 | B21: 2000 | C21: =B22 | D21: =C22 | E21: =B21
A22: 期末現金残高 | B22: =B21+B20 | C22: =C21+C20 | D22: =D21+D20 | E22: =D22
A24: ✓ BS現金との差異（0が正常） | B24: =B22-BS（貸借対照表）!C5 | C24: =C22-BS（貸借対照表）!D5 | D24: =D22-BS（貸借対照表）!E5

Sheet 感度分析
A1: UNLID 感度分析——売上成長率 × 原価率 → 営業利益への影響
A2: 単位：万円 | Year2を基準にした2軸感度分析（売上成長率 × 原価率）
A4: 【分析①】Year2 営業利益：売上成長率 × 原価率
A5: Year1売上実績（万円） | B5: =PL（損益計算書）!B8
A6: Year2 販管費固定額（万円） | B6: =PL（損益計算書）!C29
A7: 【見方】縦：売上成長率、横：原価率（売上に対する割合）
A9: 売上成長率 \ 原価率 | B9: 0.05 | C9: 0.08 | D9: 0.1 | E9: 0.12 | F9: 0.15 | G9: 0.18 | H9: 0.2
A10: 2 | B10: =$B$5*2.0*(1-B$9)-$B$6 | C10: =$B$5*2.0*(1-C$9)-$B$6 | D10: =$B$5*2.0*(1-D$9)-$B$6 | E10: =$B$5*2.0*(1-E$9)-$B$6 | F10: =$B$5*2.0*(1-F$9)-$B$6 | G10: =$B$5*2.0*(1-G$9)-$B$6 | H10: =$B$5*2.0*(1-H$9)-$B$6
A11: 3 | B11: =$B$5*3.0*(1-B$9)-$B$6 | C11: =$B$5*3.0*(1-C$9)-$B$6 | D11: =$B$5*3.0*(1-D$9)-$B$6 | E11: =$B$5*3.0*(1-E$9)-$B$6 | F11: =$B$5*3.0*(1-F$9)-$B$6 | G11: =$B$5*3.0*(1-G$9)-$B$6 | H11: =$B$5*3.0*(1-H$9)-$B$6
A12: 4 | B12: =$B$5*4.0*(1-B$9)-$B$6 | C12: =$B$5*4.0*(1-C$9)-$B$6 | D12: =$B$5*4.0*(1-D$9)-$B$6 | E12: =$B$5*4.0*(1-E$9)-$B$6 | F12: =$B$5*4.0*(1-F$9)-$B$6 | G12: =$B$5*4.0*(1-G$9)-$B$6 | H12: =$B$5*4.0*(1-H$9)-$B$6
A13: 5 | B13: =$B$5*5.0*(1-B$9)-$B$6 | C13: =$B$5*5.0*(1-C$9)-$B$6 | D13: =$B$5*5.0*(1-D$9)-$B$6 | E13: =$B$5*5.0*(1-E$9)-$B$6 | F13: =$B$5*5.0*(1-F$9)-$B$6 | G13: =$B$5*5.0*(1-G$9)-$B$6 | H13: =$B$5*5.0*(1-H$9)-$B$6
A14: 6 | B14: =$B$5*6.0*(1-B$9)-$B$6 | C14: =$B$5*6.0*(1-C$9)-$B$6 | D14: =$B$5*6.0*(1-D$9)-$B$6 | E14: =$B$5*6.0*(1-E$9)-$B$6 | F14: =$B$5*6.0*(1-F$9)-$B$6 | G14: =$B$5*6.0*(1-G$9)-$B$6 | H14: =$B$5*6.0*(1-H$9)-$B$6
A15: 7 | B15: =$B$5*7.0*(1-B$9)-$B$6 | C15: =$B$5*7.0*(1-C$9)-$B$6 | D15: =$B$5*7.0*(1-D$9)-$B$6 | E15: =$B$5*7.0*(1-E$9)-$B$6 | F15: =$B$5*7.0*(1-F$9)-$B$6 | G15: =$B$5*7.0*(1-G$9)-$B$6 | H15: =$B$5*7.0*(1-H$9)-$B$6
A16: 8 | B16: =$B$5*8.0*(1-B$9)-$B$6 | C16: =$B$5*8.0*(1-C$9)-$B$6 | D16: =$B$5*8.0*(1-D$9)-$B$6 | E16: =$B$5*8.0*(1-E$9)-$B$6 | F16: =$B$5*8.0*(1-F$9)-$B$6 | G16: =$B$5*8.0*(1-G$9)-$B$6 | H16: =$B$5*8.0*(1-H$9)-$B$6
A17: 10 | B17: =$B$5*10.0*(1-B$9)-$B$6 | C17: =$B$5*10.0*(1-C$9)-$B$6 | D17: =$B$5*10.0*(1-D$9)-$B$6 | E17: =$B$5*10.0*(1-E$9)-$B$6 | F17: =$B$5*10.0*(1-F$9)-$B$6 | G17: =$B$5*10.0*(1-G$9)-$B$6 | H17: =$B$5*10.0*(1-H$9)-$B$6
A19: ※ 原価率 = (ワーカー報酬+外注費) / 売上高。現状モデルは約8〜9%。
A22: 【分析②】Year2 売上：B2B契約社数 × 月額単価
A23: 人材紹介フィー固定（Year2）（万円） | B23: =PL（損益計算書）!C6
A25: 契約社数 \ 月額単価（万円） | B25: 13 | C25: 15 | D25: 17 | E25: 18 | F25: 20 | G25: 22 | H25: 25
A26: 20 | B26: =20*13*12+$B$23 | C26: =20*15*12+$B$23 | D26: =20*17*12+$B$23 | E26: =20*18*12+$B$23 | F26: =20*20*12+$B$23 | G26: =20*22*12+$B$23 | H26: =20*25*12+$B$23
A27: 30 | B27: =30*13*12+$B$23 | C27: =30*15*12+$B$23 | D27: =30*17*12+$B$23 | E27: =30*18*12+$B$23 | F27: =30*20*12+$B$23 | G27: =30*22*12+$B$23 | H27: =30*25*12+$B$23
A28: 40 | B28: =40*13*12+$B$23 | C28: =40*15*12+$B$23 | D28: =40*17*12+$B$23 | E28: =40*18*12+$B$23 | F28: =40*20*12+$B$23 | G28: =40*22*12+$B$23 | H28: =40*25*12+$B$23
A29: 50 | B29: =50*13*12+$B$23 | C29: =50*15*12+$B$23 | D29: =50*17*12+$B$23 | E29: =50*18*12+$B$23 | F29: =50*20*12+$B$23 | G29: =50*22*12+$B$23 | H29: =50*25*12+$B$23
A30: 60 | B30: =60*13*12+$B$23 | C30: =60*15*12+$B$23 | D30: =60*17*12+$B$23 | E30: =60*18*12+$B$23 | F30: =60*20*12+$B$23 | G30: =60*22*12+$B$23 | H30: =60*25*12+$B$23
A31: 70 | B31: =70*13*12+$B$23 | C31: =70*15*12+$B$23 | D31: =70*17*12+$B$23 | E31: =70*18*12+$B$23 | F31: =70*20*12+$B$23 | G31: =70*22*12+$B$23 | H31: =70*25*12+$B$23
A32: 80 | B32: =80*13*12+$B$23 | C32: =80*15*12+$B$23 | D32: =80*17*12+$B$23 | E32: =80*18*12+$B$23 | F32: =80*20*12+$B$23 | G32: =80*22*12+$B$23 | H32: =80*25*12+$B$23
A36: 【分析③】3シナリオ営業利益比較（Year1〜3）
A37: シナリオ | B37: Year1売上 | C37: Year1営業利益 | D37: Year2売上 | E37: Year2営業利益 | F37: Year3売上 | G37: Year3営業利益
A38: 楽観 | B38: 2886 | C38: -60 | D38: 20160 | E38: 8100 | F38: 66920 | G38: 29600
A39: 中央値（ベース） | B39: =PL（損益計算書）!B8 | C39: =PL（損益計算書）!B32 | D39: =PL（損益計算書）!C8 | E39: =PL（損益計算書）!C32 | F39: =PL（損益計算書）!D8 | G39: =PL（損益計算書）!D32
A40: 保守 | B40: 1554 | C40: -240 | D40: 7920 | E40: 1350 | F40: 28680 | G40: 7400
A42: 楽観：FDE採用×1.3倍・B2B契約×1.3倍 保守：FDE採用×0.7倍・B2B契約×0.55倍
